README.rst
setup.py
cmipdata/__init__.py
cmipdata/classes.py
cmipdata/loading_tools.py
cmipdata/plotting_tools.py
cmipdata/preprocessing_tools.py
cmipdata/slice_nc.py
cmipdata.egg-info/PKG-INFO
cmipdata.egg-info/SOURCES.txt
cmipdata.egg-info/dependency_links.txt
cmipdata.egg-info/requires.txt
cmipdata.egg-info/top_level.txt