Metadata-Version: 1.1
Name: cmipdata
Version: 0.7
Summary: Processing tools for large ensembles of CMIP type netcdf data
Home-page: https://github.com/swartn/cmipdata
Author: Neil C. Swart
Author-email: Neil.Swart@canada.ca
License: LICENSE.txt
Download-URL: https://github.com/swartn/cmipdata/archive/v0.7.zip
Keywords: climate,data,CMIP5,CMIP6,NetCDF,analysis,processing
Platform: UNKNOWN
